tool_box/__init__.py
tool_box/key_typer/__init__.py
tool_box/key_typer/keyboard_tools.py
thunder_toolbox-0.0.5.dist-info/LICENCE.txt
thunder_toolbox-0.0.5.dist-info/METADATA
thunder_toolbox-0.0.5.dist-info/WHEEL
thunder_toolbox-0.0.5.dist-info/top_level.txt
thunder_toolbox-0.0.5.dist-info/RECORD
