Metadata-Version: 2.1
Name: thunder-toolbox
Version: 0.0.5
Summary: Awsome tool box for python
Author: V HARSHA VARDHAN
Author-email: v.harshavardhan3@gmail.com
Classifier: Programming Language :: Python :: 3
Classifier: Operating System :: OS Independent
Classifier: License :: OSI Approved :: MIT License
License-File: LICENCE.txt
Requires-Dist: PyAutoGUI (==0.9.53)
